[
  {
    "name": "Remove Happiness System",          // branch name
    "era": "Ancient era",
    "policies": [
      {
        "name": "Remove Happiness System",      // opener: must match branch name
        "row": 0,
        "column": 0,
        "uniques": [
          "[-100]% Unhappiness from [Population] [in all cities]",
          "[-100]% Unhappiness from [Specialists] [in all cities]",
          "[-100]% Unhappiness from [Unemployed] [in all cities]"
        ]
      },
      {
        "name": "Remove Happiness System Complete",  // finisher
        "uniques": []
      }
    ]
  }
]